lifecycle_msgs/_dummy.cpython-312-x86_64-linux-gnu.so
ros_lifecycle_msgs-2.3.0.data/data/include/lifecycle_msgs/lifecycle_msgs/msg/rosidl_generator_c__visibility_control.h
ros_lifecycle_msgs-2.3.0.data/data/include/lifecycle_msgs/lifecycle_msgs/msg/rosidl_generator_cpp__visibility_control.hpp
ros_lifecycle_msgs-2.3.0.data/data/include/lifecycle_msgs/lifecycle_msgs/msg/rosidl_typesupport_fastrtps_c__visibility_control.h
ros_lifecycle_msgs-2.3.0.data/data/include/lifecycle_msgs/lifecycle_msgs/msg/rosidl_typesupport_fastrtps_cpp__visibility_control.h
ros_lifecycle_msgs-2.3.0.data/data/include/lifecycle_msgs/lifecycle_msgs/msg/rosidl_typesupport_introspection_c__visibility_control.h
ros_lifecycle_msgs-2.3.0.data/data/include/lifecycle_msgs/lifecycle_msgs/msg/state.h
ros_lifecycle_msgs-2.3.0.data/data/include/lifecycle_msgs/lifecycle_msgs/msg/state.hpp
ros_lifecycle_msgs-2.3.0.data/data/include/lifecycle_msgs/lifecycle_msgs/msg/transition.h
ros_lifecycle_msgs-2.3.0.data/data/include/lifecycle_msgs/lifecycle_msgs/msg/transition.hpp
ros_lifecycle_msgs-2.3.0.data/data/include/lifecycle_msgs/lifecycle_msgs/msg/transition_description.h
ros_lifecycle_msgs-2.3.0.data/data/include/lifecycle_msgs/lifecycle_msgs/msg/transition_description.hpp
ros_lifecycle_msgs-2.3.0.data/data/include/lifecycle_msgs/lifecycle_msgs/msg/transition_event.h
ros_lifecycle_msgs-2.3.0.data/data/include/lifecycle_msgs/lifecycle_msgs/msg/transition_event.hpp
ros_lifecycle_msgs-2.3.0.data/data/include/lifecycle_msgs/lifecycle_msgs/msg/detail/state__builder.hpp
ros_lifecycle_msgs-2.3.0.data/data/include/lifecycle_msgs/lifecycle_msgs/msg/detail/state__description.c
ros_lifecycle_msgs-2.3.0.data/data/include/lifecycle_msgs/lifecycle_msgs/msg/detail/state__functions.c
ros_lifecycle_msgs-2.3.0.data/data/include/lifecycle_msgs/lifecycle_msgs/msg/detail/state__functions.h
ros_lifecycle_msgs-2.3.0.data/data/include/lifecycle_msgs/lifecycle_msgs/msg/detail/state__rosidl_typesupport_fastrtps_c.h
ros_lifecycle_msgs-2.3.0.data/data/lib/python3.12/site-packages/lifecycle_msgs-2.3.0-py3.12.egg-info/PKG-INFO
ros_lifecycle_msgs-2.3.0.data/data/lib/python3.12/site-packages/lifecycle_msgs-2.3.0-py3.12.egg-info/SOURCES.txt
ros_lifecycle_msgs-2.3.0.data/data/lib/python3.12/site-packages/lifecycle_msgs-2.3.0-py3.12.egg-info/dependency_links.txt
ros_lifecycle_msgs-2.3.0.data/data/lib/python3.12/site-packages/lifecycle_msgs-2.3.0-py3.12.egg-info/top_level.txt
ros_lifecycle_msgs-2.3.0.dist-info/METADATA
ros_lifecycle_msgs-2.3.0.dist-info/WHEEL
ros_lifecycle_msgs-2.3.0.dist-info/top_level.txt
ros_lifecycle_msgs-2.3.0.dist-info/RECORD
