Metadata-Version: 2.4
Name: ros-lifecycle-msgs
Version: 2.3.0
Summary: A ROS package providing message and service definitions for managing lifecycle node state-machines.
Requires-Dist: ros-rosidl-default-runtime~=1.7.1
Dynamic: description
Dynamic: description-content-type
Dynamic: requires-dist
Dynamic: summary
